jswipl/__init__.py
jswipl/jupyter.py
jswipl/swipl.py
jswipl/test.py
jswipl-1.0.2.dist-info/LICENSE
jswipl-1.0.2.dist-info/METADATA
jswipl-1.0.2.dist-info/WHEEL
jswipl-1.0.2.dist-info/entry_points.txt
jswipl-1.0.2.dist-info/top_level.txt
jswipl-1.0.2.dist-info/RECORD
