Metadata-Version: 2.1
Name: jswipl
Version: 1.0.2
Summary: A Jupyter Kernel for SWI-Prolog.
Home-page: https://github.com/targodan/jupyter-swi-prolog
Author: Luca Corbatto
Author-email: luca-pip@corbatto.de
License: UNKNOWN
Platform: UNKNOWN
Classifier: Programming Language :: Python :: 3
Classifier: License :: OSI Approved :: MIT License
Classifier: Operating System :: OS Independent
